nining/__init__.py
nining/app.py
nining/constant.py
nining/errors.py
nining/logs.py
nining/contrib/__init__.py
nining/contrib/third.py
nining-0.0.1.dist-info/METADATA
nining-0.0.1.dist-info/WHEEL
nining-0.0.1.dist-info/top_level.txt
nining-0.0.1.dist-info/RECORD
