Metadata-Version: 2.1
Name: nining
Version: 0.0.1
Summary: First process about setuptools
Home-page: https://ni-ning.cn
Author: nining
Author-email: nining1314@gmail.com
License: MIT
Platform: UNKNOWN
